Metadata-Version: 2.1
Name: test-search-es-client
Version: 1.2.2
Summary: to search es client and record log
Home-page: UNKNOWN
Author: 
Author-email: 
License: UNKNOWN
Platform: UNKNOWN
Classifier: Programming Language :: Python :: 3
Classifier: License :: OSI Approved :: MIT License
Classifier: Operating System :: OS Independent
Requires-Python: >=3.6
